{
  "name": "Content",
  "resourcesDir": "Content",
  "template": {
    "timeline": {
      "tracks": [
        {
          "clips": [
            {
              "asset": {
                "type": "video",
                "src": "{{Content/1-Avatar.mov}}",
                "trim": 0
              },
              "start": 0.0,
              "length": 1.8,
              "fit": "cover",
              "effect": "zoomIn",
              "transition": {
                "in": "zoom"
              }
            },
            {
              "asset": {
                "type": "video",
                "src": "{{Content/1-Avatar.mov}}",
                "trim": 860
              },
              "start": 1.8,
              "length": 1.2,
              "fit": "cover"
            },
            {
              "asset": {
                "type": "video",
                "src": "{{Content/2-Ustal.mp4}}",
                "trim": 180
              },
              "start": 3.0,
              "length": 1.5,
              "fit": "cover"
            },
            {
              "asset": {
                "type": "video",
                "src": "{{Content/3-Girl.mp4}}",
                "trim": 740
              },
              "start": 4.5,
              "length": 1.6,
              "fit": "cover"
            },
            {
              "asset": {
                "type": "video",
                "src": "{{Content/1-Avatar.mov}}",
                "trim": 460
              },
              "start": 6.1,
              "length": 2.2,
              "fit": "cover"
            },
            {
              "asset": {
                "type": "video",
                "src": "{{Content/1-Avatar.mov}}",
                "trim": 780
              },
              "start": 8.3,
              "length": 1.6,
              "fit": "cover"
            },
            {
              "asset": {
                "type": "video",
                "src": "{{Content/4-Content.mov}}",
                "trim": 1440
              },
              "start": 9.9,
              "length": 1.0,
              "fit": "cover"
            },
            {
              "asset": {
                "type": "video",
                "src": "{{Content/1-Avatar.mov}}",
                "trim": 1500
              },
              "start": 10.9,
              "length": 2.5,
              "fit": "cover",
              "effect": "zoomIn",
              "transition": {
                "in": "zoom"
              }
            },
            {
              "asset": {
                "type": "video",
                "src": "{{Content/5-Analitic.mp4}}",
                "trim": 1180
              },
              "start": 13.4,
              "length": 3.0,
              "fit": "cover"
            },
            {
              "asset": {
                "type": "video",
                "src": "{{Content/1-Avatar.mov}}",
                "trim": 1360
              },
              "start": 16.4,
              "length": 2.1,
              "fit": "cover",
              "effect": "zoomIn",
              "transition": {
                "in": "zoom"
              }
            }
          ]
        },
        {
          "clips": [
            {
              "asset": {
                "type": "audio",
                "src": "{{Content/click.wav}}",
                "volume": 0.7
              },
              "start": 1.8,
              "length": 1.2
            },
            {
              "asset": {
                "type": "audio",
                "src": "{{Content/whoosh.wav}}",
                "volume": 0.7
              },
              "start": 3.0,
              "length": 1.5
            },
            {
              "asset": {
                "type": "audio",
                "src": "{{Content/whoosh.wav}}",
                "volume": 0.7
              },
              "start": 4.5,
              "length": 1.6
            },
            {
              "asset": {
                "type": "audio",
                "src": "{{Content/click.wav}}",
                "volume": 0.7
              },
              "start": 8.3,
              "length": 1.6
            },
            {
              "asset": {
                "type": "audio",
                "src": "{{Content/whoosh.wav}}",
                "volume": 0.7
              },
              "start": 10.9,
              "length": 2.5
            },
            {
              "asset": {
                "type": "audio",
                "src": "{{Content/camera-shutter.wav}}",
                "volume": 0.7
              },
              "start": 13.4,
              "length": 3.0
            },
            {
              "asset": {
                "type": "audio",
                "src": "{{Content/whoosh.wav}}",
                "volume": 0.7
              },
              "start": 16.4,
              "length": 2.1
            }
          ]
        }
      ],
      "background": "#000000"
    },
    "output": {
      "format": "mp4",
      "resolution": "sd",
      "aspectRatio": "9:16",
      "fps": 30
    }
  },
  "merge": [
    {
      "find": "Content/1-Avatar.mov",
      "replace": ""
    },
    {
      "find": "Content/1-Avatar.mov",
      "replace": ""
    },
    {
      "find": "Content/2-Ustal.mp4",
      "replace": ""
    },
    {
      "find": "Content/3-Girl.mp4",
      "replace": ""
    },
    {
      "find": "Content/1-Avatar.mov",
      "replace": ""
    },
    {
      "find": "Content/1-Avatar.mov",
      "replace": ""
    },
    {
      "find": "Content/4-Content.mov",
      "replace": ""
    },
    {
      "find": "Content/1-Avatar.mov",
      "replace": ""
    },
    {
      "find": "Content/5-Analitic.mp4",
      "replace": ""
    },
    {
      "find": "Content/1-Avatar.mov",
      "replace": ""
    },
    {
      "find": "Content/click.wav",
      "replace": ""
    },
    {
      "find": "Content/whoosh.wav",
      "replace": ""
    },
    {
      "find": "Content/whoosh.wav",
      "replace": ""
    },
    {
      "find": "Content/click.wav",
      "replace": ""
    },
    {
      "find": "Content/whoosh.wav",
      "replace": ""
    },
    {
      "find": "Content/camera-shutter.wav",
      "replace": ""
    },
    {
      "find": "Content/whoosh.wav",
      "replace": ""
    }
  ]
}